oddhash/__init__.py
oddhash/args.py
oddhash/crack.py
oddhash/main.py
oddhash-0.0.6.dist-info/LICENSE
oddhash-0.0.6.dist-info/METADATA
oddhash-0.0.6.dist-info/WHEEL
oddhash-0.0.6.dist-info/entry_points.txt
oddhash-0.0.6.dist-info/top_level.txt
oddhash-0.0.6.dist-info/RECORD
