Metadata-Version: 2.1
Name: oddhash
Version: 0.0.6
Summary: Tool to hash odd format passwords.
Home-page: https://github.com/kazkansouh/odd-hash
Author: Karim Kanso
Author-email: kaz.kanso@gmail.com
License: UNKNOWN
Platform: UNKNOWN
Classifier: Programming Language :: Python :: 3
Classifier: License :: OSI Approved :: GNU General Public License v3 (GPLv3)
Classifier: Operating System :: OS Independent
Classifier: Topic :: Security :: Cryptography
Requires-Dist: lark-parser
Requires-Dist: pycryptodome
